occupationcoder/__init__.py
occupationcoder/coder/__init__.py
occupationcoder/coder/coder.py
occupationcoder/createdictionaries/__init__.py
occupationcoder/createdictionaries/generate_expand_dict.py
occupationcoder/createdictionaries/prepare_ONS_titles.py
occupationcoder/createdictionaries/remove_words_not_in_ONS.py
occupationcoder/dictionaries/ONS_index.xls
occupationcoder/dictionaries/expand_dict.json
occupationcoder/dictionaries/known_words_dict.json
occupationcoder/dictionaries/mg_buckets_ons_df_processed.json
occupationcoder/dictionaries/replace_lookup_abbreviations.csv
occupationcoder/dictionaries/titles_mg_ons_nodesc.json
occupationcoder/dictionaries/titles_minor_group_ons.json
occupationcoder/dictionaries/words_not_in_replace_lookupONLYfreq3Abovwe.csv
occupationcoder/utilities/__init__.py
occupationcoder/utilities/utilities.py
occupationcoder-0.2.0.dist-info/AUTHORS.rst
occupationcoder-0.2.0.dist-info/LICENSE
occupationcoder-0.2.0.dist-info/METADATA
occupationcoder-0.2.0.dist-info/WHEEL
occupationcoder-0.2.0.dist-info/top_level.txt
occupationcoder-0.2.0.dist-info/RECORD
