Metadata-Version: 2.1
Name: occupationcoder
Version: 0.2.0
Summary: A tool to use job text, such as job description, to assign standard occupational classification codes.
Home-page: https://github.com/aeturrell/occupationcoder
Author: Arthur Turrell and Jyldyz Djumalieva
Author-email: 
License: Custom
Keywords: occupationcoder
Platform: UNKNOWN
Classifier: Development Status :: 2 - Pre-Alpha
Classifier: Intended Audience :: Developers
Classifier: License :: OSI Approved :: GNU General Public License v3 (GPLv3)
Classifier: Natural Language :: English
Classifier: Programming Language :: Python :: 3
Classifier: Programming Language :: Python :: 3.5
Classifier: Programming Language :: Python :: 3.6
Classifier: Programming Language :: Python :: 3.7
Classifier: Programming Language :: Python :: 3.8
Requires-Python: >=3.5
Requires-Dist: pandas
Requires-Dist: scikit-learn
Requires-Dist: nltk
Requires-Dist: dask
Requires-Dist: beautifulsoup4
